zhinst/hdiq/__init__.py
zhinst/hdiq/hdiq.py
zhinst/hdiq/utils.py
zhinst_hdiq-1.0.2.dist-info/LICENSE
zhinst_hdiq-1.0.2.dist-info/METADATA
zhinst_hdiq-1.0.2.dist-info/WHEEL
zhinst_hdiq-1.0.2.dist-info/RECORD
