Metadata-Version: 2.1
Name: zhinst-hdiq
Version: 1.0.2
Summary: API for Zurich Instruments HDIQ devices
Home-page: https://www.zhinst.com/products/hdiq-iq-modulator
Author: Zurich Instruments AG
Author-email: info@zhinst.com
Maintainer: Matthias Berg
Maintainer-email: matthias.berg@zhinst.com
Requires-Python: >=3.7,<4.0
Classifier: Programming Language :: Python :: 3
Classifier: Programming Language :: Python :: 3.7
Classifier: Programming Language :: Python :: 3.8
Classifier: Programming Language :: Python :: 3.9
Classifier: Programming Language :: Python :: 3.10
Classifier: Programming Language :: Python :: 3.11
Requires-Dist: ifaddr (>=0.1.7,<0.2.0)
Project-URL: Repository, https://github.com/zhinst/zhinst-hdiq
